tocketry/__init__.py
tocketry/_base.py
tocketry/_setup.py
tocketry/_version.py
tocketry/application.py
tocketry/exc.py
tocketry/session.py
tocketry/test.py
tocketry/args/__init__.py
tocketry/args/builtin.py
tocketry/args/secret.py
tocketry/conditions/__init__.py
tocketry/conditions/api.py
tocketry/conditions/func.py
tocketry/conditions/meta.py
tocketry/conditions/parameter.py
tocketry/conditions/scheduler.py
tocketry/conditions/time.py
tocketry/conditions/task/__init__.py
tocketry/conditions/task/task.py
tocketry/conditions/task/utils.py
tocketry/conds/__init__.py
tocketry/core/__init__.py
tocketry/core/hook.py
tocketry/core/schedule.py
tocketry/core/task.py
tocketry/core/condition/__init__.py
tocketry/core/condition/base.py
tocketry/core/log/__init__.py
tocketry/core/log/adapter.py
tocketry/core/parameters/__init__.py
tocketry/core/parameters/arguments.py
tocketry/core/parameters/parameters.py
tocketry/core/time/__init__.py
tocketry/core/time/anchor.py
tocketry/core/time/base.py
tocketry/core/time/utils.py
tocketry/core/utils/__init__.py
tocketry/core/utils/meta.py
tocketry/core/utils/pickle.py
tocketry/core/utils/process.py
tocketry/log/__init__.py
tocketry/log/defaults.py
tocketry/log/handlers.py
tocketry/log/log_record.py
tocketry/log/utils.py
tocketry/parameters/__init__.py
tocketry/parameters/func.py
tocketry/parse/__init__.py
tocketry/parse/_setup_cond_parsers.py
tocketry/parse/condition.py
tocketry/parse/time.py
tocketry/parse/_condition/__init__.py
tocketry/parse/_condition/condition_item.py
tocketry/parse/_condition/string.py
tocketry/parse/_time/__init__.py
tocketry/parse/_time/string.py
tocketry/parse/_time/time_item.py
tocketry/parse/utils/__init__.py
tocketry/parse/utils/cond.py
tocketry/parse/utils/exception.py
tocketry/parse/utils/parser.py
tocketry/parse/utils/string_parser.py
tocketry/parse/utils/utils.py
tocketry/pybox/__init__.py
tocketry/pybox/container/__init__.py
tocketry/pybox/container/visitor.py
tocketry/pybox/pkg/__init__.py
tocketry-0.1.0.dist-info/licenses/LICENSE
tocketry-0.1.0.dist-info/METADATA
tocketry-0.1.0.dist-info/WHEEL
tocketry-0.1.0.dist-info/top_level.txt
tocketry-0.1.0.dist-info/RECORD
