Metadata-Version: 2.4
Name: tocketry
Version: 0.1.0
Summary: Advanced scheduling framework
Author-email: Mikael Koli <koli.mikael@gmail.com>, Josh Pearson <pearson.josh@outlook.com>
License-Expression: MIT
Project-URL: Homepage, https://github.com/jypear/tocketry
Project-URL: Documentation, https://tocketry.readthedocs.io
Project-URL: Source, https://github.com/Jypear/tocketry
Project-URL: Changelog, https://tocketry.readthedocs.io/en/stable/versions.html
Classifier: Operating System :: OS Independent
Classifier: Programming Language :: Python
Classifier: Programming Language :: Python :: 3
Classifier: Programming Language :: Python :: 3.7
Classifier: Programming Language :: Python :: 3.8
Classifier: Programming Language :: Python :: 3.9
Classifier: Programming Language :: Python :: 3.10
Classifier: Programming Language :: Python :: 3.11
Classifier: Topic :: System
Classifier: Topic :: Software Development
Classifier: Topic :: Software Development :: Libraries
Classifier: Topic :: Software Development :: Libraries :: Application Frameworks
Classifier: Topic :: Office/Business :: Scheduling
Classifier: Intended Audience :: Developers
Classifier: Intended Audience :: System Administrators
Classifier: Intended Audience :: Information Technology
Requires-Python: >=3.7
License-File: LICENSE
Requires-Dist: python-dateutil
Provides-Extra: test
Requires-Dist: pytest; extra == "test"
Requires-Dist: pytest-asyncio; extra == "test"
Provides-Extra: docs
Requires-Dist: sphinx>=1.7.5; extra == "docs"
Requires-Dist: pydata-sphinx-theme; extra == "docs"
Requires-Dist: sphinx_book_theme; extra == "docs"
Requires-Dist: sphinx-copybutton; extra == "docs"
Requires-Dist: sphinx-material; extra == "docs"
Dynamic: license-file
